wadiroscnn/__init__.py
wadiroscnn/models.py
wadiroscnn-0.6.dist-info/LICENSE
wadiroscnn-0.6.dist-info/METADATA
wadiroscnn-0.6.dist-info/WHEEL
wadiroscnn-0.6.dist-info/top_level.txt
wadiroscnn-0.6.dist-info/RECORD
